morast/__init__.py
morast/__main__.py
morast/capabilities.py
morast/commandline.py
morast/commons.py
morast/configuration.py
morast/core.py
morast/nodes.py
morast/overrides.py
morast/py.typed
morast/reference.py
morast-0.3.5.dist-info/LICENSE
morast-0.3.5.dist-info/METADATA
morast-0.3.5.dist-info/WHEEL
morast-0.3.5.dist-info/entry_points.txt
morast-0.3.5.dist-info/top_level.txt
morast-0.3.5.dist-info/RECORD
