Metadata-Version: 2.1
Name: morast
Version: 0.3.5
Summary: Module reference by analyzing the syntax tree
Author-email: Rainer Schwarzbach <rainer@blackstream.de>
License: MIT License
Project-URL: Homepage, https://gitlab.com/blackstream-x/morast
Project-URL: Documentation, https://blackstream-x.gitlab.io/morast
Project-URL: CI, https://gitlab.com/blackstream-x/morast/-/pipelines
Project-URL: Bug Tracker, https://gitlab.com/blackstream-x/morast/-/issues
Project-URL: Repository, https://gitlab.com/blackstream-x/morast.git
Keywords: ast,documentation
Classifier: Development Status :: 4 - Beta
Classifier: License :: OSI Approved :: MIT License
Classifier: Operating System :: OS Independent
Classifier: Programming Language :: Python :: 3
Classifier: Programming Language :: Python :: 3.9
Classifier: Programming Language :: Python :: 3.10
Classifier: Programming Language :: Python :: 3.11
Classifier: Programming Language :: Python :: 3.12
Classifier: Programming Language :: Python :: 3.13
Classifier: Programming Language :: Python :: 3 :: Only
Classifier: Topic :: Software Development :: Documentation
Classifier: Topic :: Software Development :: Libraries :: Python Modules
Classifier: Topic :: Software Development :: Pre-processors
Classifier: Topic :: Text Processing :: Markup :: Markdown
Classifier: Intended Audience :: Developers
Requires-Python: >=3.9
License-File: LICENSE
Requires-Dist: PyYAML >=6.0.1
Requires-Dist: smdg >=0.2.0
